{
  "minecraft:recipes/decorations/snow": {
    "criteria": {
      "has_snowball": "2022-06-16 16:40:15 +0000"
    },
    "done": true
  },
  "minecraft:recipes/building_blocks/crimson_planks": {
    "criteria": {
      "has_logs": "2022-06-16 16:39:49 +0000"
    },
    "done": true
  },
  "minecraft:adventure/root": {
    "criteria": {
      "killed_by_something": "2022-06-16 16:39:52 +0000"
    },
    "done": true
  },
  "minecraft:recipes/building_blocks/crimson_hyphae": {
    "criteria": {
      "has_log": "2022-06-16 16:39:49 +0000"
    },
    "done": true
  },
  "minecraft:recipes/food/cake": {
    "criteria": {
      "has_egg": "2022-06-16 16:40:00 +0000"
    },
    "done": true
  },
  "minecraft:recipes/building_blocks/snow_block": {
    "criteria": {
      "has_snowball": "2022-06-16 16:40:15 +0000"
    },
    "done": true
  },
  "minecraft:adventure/adventuring_time": {
    "criteria": {
      "minecraft:wooded_badlands": "2022-06-16 16:40:13 +0000",
      "minecraft:stony_shore": "2022-06-16 16:39:46 +0000"
    },
    "done": false
  },
  "DataVersion": 2975
}